mypackage/__init__.py
pybites_poetry_stub-0.2.0.dist-info/WHEEL
pybites_poetry_stub-0.2.0.dist-info/METADATA
pybites_poetry_stub-0.2.0.dist-info/RECORD
